aliyunsdkmpaas/__init__.py
aliyunsdkmpaas/endpoint.py
aliyunsdkmpaas/request/__init__.py
aliyunsdkmpaas/request/v20190821/ChangeMcubeMiniTaskStatusRequest.py
aliyunsdkmpaas/request/v20190821/CreateMcubeMiniAppRequest.py
aliyunsdkmpaas/request/v20190821/CreateMcubeMiniTaskRequest.py
aliyunsdkmpaas/request/v20190821/CreateMcubeVhostRequest.py
aliyunsdkmpaas/request/v20190821/CreateMcubeWhitelistForIdeRequest.py
aliyunsdkmpaas/request/v20190821/CreateMcubeWhitelistRequest.py
aliyunsdkmpaas/request/v20190821/CreateMsaEnhanceRequest.py
aliyunsdkmpaas/request/v20190821/CreateOpenGlobalDataRequest.py
aliyunsdkmpaas/request/v20190821/CreateOpenSingleDataRequest.py
aliyunsdkmpaas/request/v20190821/DeleteMcubeMiniAppRequest.py
aliyunsdkmpaas/request/v20190821/DeleteMcubeWhitelistRequest.py
aliyunsdkmpaas/request/v20190821/DeleteMpaasMrtcArtvcRecordfileRequest.py
aliyunsdkmpaas/request/v20190821/ExistMcubeRsaKeyRequest.py
aliyunsdkmpaas/request/v20190821/ExportMappCenterAppConfigRequest.py
aliyunsdkmpaas/request/v20190821/GetMcubeFileTokenRequest.py
aliyunsdkmpaas/request/v20190821/ListMPaaSMasTinyAppRequest.py
aliyunsdkmpaas/request/v20190821/ListMappCenterAppsRequest.py
aliyunsdkmpaas/request/v20190821/ListMappCenterWorkspacesRequest.py
aliyunsdkmpaas/request/v20190821/ListMcdpAimRequest.py
aliyunsdkmpaas/request/v20190821/ListMcubeMiniAppsRequest.py
aliyunsdkmpaas/request/v20190821/ListMcubeMiniPackagesRequest.py
aliyunsdkmpaas/request/v20190821/ListMcubeMiniTasksRequest.py
aliyunsdkmpaas/request/v20190821/ListMcubeWhitelistsRequest.py
aliyunsdkmpaas/request/v20190821/ListMgsApiRequest.py
aliyunsdkmpaas/request/v20190821/PushBroadcastRequest.py
aliyunsdkmpaas/request/v20190821/PushMultipleRequest.py
aliyunsdkmpaas/request/v20190821/PushSimpleRequest.py
aliyunsdkmpaas/request/v20190821/PushTemplateRequest.py
aliyunsdkmpaas/request/v20190821/QueryMPaaSMasTinyAppDailyDataRequest.py
aliyunsdkmpaas/request/v20190821/QueryMPaaSMasTinyAppDailyPageViewRequest.py
aliyun_python_sdk_mpaas-1.0.0.dist-info/LICENSE
aliyun_python_sdk_mpaas-1.0.0.dist-info/METADATA
aliyun_python_sdk_mpaas-1.0.0.dist-info/WHEEL
aliyun_python_sdk_mpaas-1.0.0.dist-info/top_level.txt
aliyun_python_sdk_mpaas-1.0.0.dist-info/RECORD
